dockerll/__init__.py
dockerll/__main__.py
dockerll/pattern.py
dockerll-0.1.0.dist-info/entry_points.txt
dockerll-0.1.0.dist-info/WHEEL
dockerll-0.1.0.dist-info/METADATA
dockerll-0.1.0.dist-info/RECORD
